list_methods/__init__.py
list_methods/main.py
list_methods-0.1.3.dist-info/LICENSE
list_methods-0.1.3.dist-info/METADATA
list_methods-0.1.3.dist-info/WHEEL
list_methods-0.1.3.dist-info/top_level.txt
list_methods-0.1.3.dist-info/RECORD
