Metadata-Version: 2.1
Name: list-methods
Version: 0.1.3
Summary: Add .map, .filter and .reduce as list methods
Home-page: https://github.com/theodorrene/list_methods
Author: Theodor René Carlsen
Author-email: theodor.rene@gmail.com
License: UNKNOWN
Project-URL: Bug Tracker, https://github.com/theodorrene/list_methods/issues
Platform: UNKNOWN
Classifier: Programming Language :: Python :: 3
Classifier: License :: OSI Approved :: GNU General Public License v3 or later (GPLv3+)
Classifier: Operating System :: OS Independent
Requires-Python: >=3.6
License-File: LICENSE
